ncagg/__init__.py
ncagg/__main__.py
ncagg/aggregator.py
ncagg/aggrelist.py
ncagg/attributes.py
ncagg/cli.py
ncagg/config.py
ncagg-0.8.18.dist-info/LICENSE
ncagg-0.8.18.dist-info/METADATA
ncagg-0.8.18.dist-info/WHEEL
ncagg-0.8.18.dist-info/entry_points.txt
ncagg-0.8.18.dist-info/top_level.txt
ncagg-0.8.18.dist-info/RECORD
