Metadata-Version: 2.1
Name: ncagg
Version: 0.8.18
Summary: Utility for aggregation of NetCDF data.
Home-page: https://github.com/5tefan/ncagg
Author: Stefan Codrescu
Author-email: stefan.codrescu@noaa.gov
Project-URL: Documentation, http://ncagg.readthedocs.io/en/latest/
Classifier: Development Status :: 5 - Production/Stable
Classifier: Intended Audience :: Science/Research
Classifier: Programming Language :: Python :: 3.7
Classifier: Programming Language :: Python :: 3.8
Classifier: Programming Language :: Python :: 3.9
Classifier: Programming Language :: Python :: 3.10
Classifier: License :: OSI Approved :: MIT License
Classifier: Operating System :: OS Independent
License-File: LICENSE
Requires-Dist: cerberus
Requires-Dist: click
Requires-Dist: numpy
Requires-Dist: netCDF4
